pdf_to_svg/__init__.py
pdf_to_svg/_core.cpp
pdf_to_svg/_core.cpython-39-aarch64-linux-gnu.so
pdf_to_svg/.libs/libcairo-script-interpreter.so
pdf_to_svg/.libs/libcairo-script-interpreter.so.2
pdf_to_svg/.libs/libcairo-script-interpreter.so.2.11805.5
pdf_to_svg/.libs/libcairo.so
pdf_to_svg/.libs/libcairo.so.2
pdf_to_svg/.libs/libcairo.so.2.11805.5
pdf_to_svg/.libs/libfreetype.so
pdf_to_svg/.libs/libfreetype.so.6
pdf_to_svg/.libs/libfreetype.so.6.20.2
pdf_to_svg/.libs/libpixman-1.so
pdf_to_svg/.libs/libpixman-1.so.0
pdf_to_svg/.libs/libpixman-1.so.0.44.2
pdf_to_svg/.libs/libpoppler.so
pdf_to_svg/.libs/libpoppler.so.156
pdf_to_svg/.libs/libpoppler.so.156.0.0
pdf_to_svg/.libs/cairo/libcairo-trace.so
pdf_to_svg.libs/libbz2-549b318a.so.1.0.6
pdf_to_svg.libs/libcairo-6abd9d87.so.2.11805.5
pdf_to_svg.libs/libfontconfig-5453315f.so.1.12.0
pdf_to_svg.libs/libfreetype-4c0e1357.so.6.20.2
pdf_to_svg.libs/libpixman-1-ccb7e278.so.0.44.2
pdf_to_svg.libs/libpng16-11aed5ca.so.16.34.0
pdf_to_svg.libs/libpoppler-567816b6.so.156.0.0
pdf_to_svg.libs/libuuid-10cee22e.so.1.3.0
pdf_to_svg-0.1.0.dist-info/METADATA
pdf_to_svg-0.1.0.dist-info/WHEEL
pdf_to_svg-0.1.0.dist-info/RECORD
pdf_to_svg-0.1.0.dist-info/licenses/LICENSE
pdf_to_svg-0.1.0.dist-info/sboms/auditwheel.cdx.json
